mscviplib-2.211201.122.dist-info/LICENSE
mscviplib-2.211201.122.dist-info/top_level.txt
mscviplib-2.211201.122.dist-info/RECORD
mscviplib-2.211201.122.dist-info/WHEEL
mscviplib-2.211201.122.dist-info/METADATA
mscviplib.libs/libz-d8a329de.so.1.2.7
mscviplib/__init__.py
mscviplib/_mscviplib.cpython-37m-x86_64-linux-gnu.so
mscviplib/test/Test_ResizeImage.py
mscviplib/test/test.jpg
mscviplib/Resources/__init__.py
mscviplib/Resources/CVIPL.bfbs
