Metadata-Version: 2.1
Name: mscviplib
Version: 2.211201.122
Summary: Python Wrapper for Microsoft Custom Vision Image Processing Library (mscviplib)
Home-page: https://docs.microsoft.com/en-us/azure/cognitive-services/custom-vision-service/
Author: Microsoft Corporation
Author-email: python@microsoft.com
License: UNKNOWN
Platform: UNKNOWN
Classifier: Development Status :: 5 - Production/Stable
Classifier: License :: OSI Approved :: MIT License
Classifier: Natural Language :: English
Classifier: Operating System :: POSIX :: Linux
Classifier: Programming Language :: Python :: 3.7
Classifier: Programming Language :: Python :: 3.8
Classifier: Programming Language :: Python :: Implementation
Classifier: Topic :: Multimedia :: Graphics
Requires-Python: >=3.7
Requires-Dist: numpy
Requires-Dist: pillow (==8.4.0)
